nlntest/ExHenon.py
nlntest/ExLogistic.py
nlntest/ExUnemployment.py
nlntest/Exmultnormrnd.py
nlntest/Exunivnorm.py
nlntest/__init__.py
nlntest-1.0.0.dist-info/METADATA
nlntest-1.0.0.dist-info/WHEEL
nlntest-1.0.0.dist-info/top_level.txt
nlntest-1.0.0.dist-info/RECORD
