Metadata-Version: 2.1
Name: nlntest
Version: 1.0.0
Summary: A Package for nonlinearity test of nuivariate and multivariate time series
Home-page: UNKNOWN
Author: Shapour Mohammadi
Author-email: shmohmad@ut.ac.ir
License: MIT
Keywords: python,Linearity Tests,Ramsey Linearity Test,Keenan Test,Tsay Test,Terasvirta, Lin and Granger Test,Lee, White and Granger Test
Platform: UNKNOWN
Requires-Python: >=3.10
Requires-Dist: numpy
Requires-Dist: pandas
Requires-Dist: pandas-datareader
Requires-Dist: statsmodels
Requires-Dist: scipy
Requires-Dist: sklearn
